.gitignore
CITATION.cff
DISCLAIMER
LICENSE
MANIFEST.in
Quickstarter.ipynb
README.md
requirements.txt
setup.cfg
setup.py
.github/ISSUE_TEMPLATE/bug_report.md
.github/ISSUE_TEMPLATE/feature_request.md
.github/workflows/build.yml
.github/workflows/draft-pdf.yml
docs/.buildinfo
docs/.nojekyll
docs/Makefile
docs/acknowledgement.html
docs/agriculture_sector.html
docs/api_docs.html
docs/authors.html
docs/commercial_sector.html
docs/contributing.html
docs/county_list.html
docs/electricity_gen_sector.html
docs/energy_production.html
docs/genindex.html
docs/getting_started.html
docs/index.html
docs/industrial_sector.html
docs/license.html
docs/make.bat
docs/mining_sector.html
docs/objects.inv
docs/public_water_sector.html
docs/py-modindex.html
docs/quickstarter.html
docs/residential_sector.html
docs/sample_data.html
docs/search.html
docs/searchindex.js
docs/transportation_sector.html
docs/user_guide.html
docs/wastewater_sector.html
docs/.doctrees/acknowledgement.doctree
docs/.doctrees/agriculture_sector.doctree
docs/.doctrees/api.doctree
docs/.doctrees/api_doc.doctree
docs/.doctrees/api_docs.doctree
docs/.doctrees/authors.doctree
docs/.doctrees/commercial_sector.doctree
docs/.doctrees/contributing.doctree
docs/.doctrees/county_list.doctree
docs/.doctrees/electricity_gen_sector.doctree
docs/.doctrees/energy_production.doctree
docs/.doctrees/environment.pickle
docs/.doctrees/getting_started.doctree
docs/.doctrees/index.doctree
docs/.doctrees/industrial_sector.doctree
docs/.doctrees/license.doctree
docs/.doctrees/mining_sector.doctree
docs/.doctrees/public_water_sector.doctree
docs/.doctrees/quickstarter.doctree
docs/.doctrees/residential_sector.doctree
docs/.doctrees/sample_data.doctree
docs/.doctrees/transportation_sector.doctree
docs/.doctrees/user_guide.doctree
docs/.doctrees/userguide.doctree
docs/.doctrees/wastewater_sector.doctree
docs/_images/bar_inflow_example.png
docs/_images/bar_outflow_example.png
docs/_images/flow_methodology_example.png
interflow.egg-info/PKG-INFO
interflow.egg-info/SOURCES.txt
interflow.egg-info/dependency_links.txt
interflow.egg-info/requires.txt
interflow.egg-info/top_level.txt
