Metadata-Version: 2.1
Name: interflow
Version: 1.0.4
Summary: An open-source Python package for calculating and organizing sectoral flows and interdependencies
Home-page: https://github.com/pnnl/interflow
Author: Kendall Mongird
Author-email: kendall.mongird@pnnl.gov
License: BSD2-Clause
Requires-Python: >=3.7
Provides-Extra: dev
License-File: LICENSE
